validate_pypi_name/__init__.py
validate_pypi_name/validator.py
validate_pypi_name-1.0.5.dist-info/LICENSE
validate_pypi_name-1.0.5.dist-info/METADATA
validate_pypi_name-1.0.5.dist-info/WHEEL
validate_pypi_name-1.0.5.dist-info/entry_points.txt
validate_pypi_name-1.0.5.dist-info/top_level.txt
validate_pypi_name-1.0.5.dist-info/RECORD
